jsonfixer/__init__.py
jsonfixer/core.py
jsonquotefixer-0.1.1.dist-info/METADATA
jsonquotefixer-0.1.1.dist-info/WHEEL
jsonquotefixer-0.1.1.dist-info/licenses/LICENSE
jsonquotefixer-0.1.1.dist-info/RECORD
