Metadata-Version: 2.4
Name: jsonquotefixer
Version: 0.1.1
Summary: Fixer for broken/unescaped quotes in pseudo-JSON text
Project-URL: Homepage, https://github.com/abzb1/jsonfixer
Project-URL: Issues, https://github.com/abzb1/jsonfixer/issues
Author-email: Hongseok Oh <cxv0519@gmail.com>
License: The MIT License
License-File: LICENSE
Keywords: fix,json,pseudo-json,quotes,repair,structured output
Classifier: Development Status :: 3 - Alpha
Classifier: Intended Audience :: Developers
Classifier: License :: OSI Approved :: MIT License
Classifier: Programming Language :: Python :: 3
Classifier: Programming Language :: Python :: 3 :: Only
Classifier: Programming Language :: Python :: 3.8
Classifier: Programming Language :: Python :: 3.9
Classifier: Programming Language :: Python :: 3.10
Classifier: Programming Language :: Python :: 3.11
Classifier: Programming Language :: Python :: 3.12
Classifier: Topic :: Software Development :: Libraries :: Python Modules
Requires-Python: >=3.8
